detect_binod.py
detect_binod-0.0.1.dist-info/LICENSE
detect_binod-0.0.1.dist-info/METADATA
detect_binod-0.0.1.dist-info/WHEEL
detect_binod-0.0.1.dist-info/top_level.txt
detect_binod-0.0.1.dist-info/RECORD
