Metadata-Version: 2.1
Name: detect-binod
Version: 0.0.1
Summary: This package will detect binod word in image file
Home-page: https://github.com/jps892/detect_binod
Author: Jeevan Prakash
Author-email: jeevan14sliet@gmail.com
License: UNKNOWN
Platform: UNKNOWN
Classifier: Programming Language :: Python :: 3
Classifier: License :: OSI Approved :: MIT License
Classifier: Operating System :: OS Independent
Requires-Python: >=3.5
Requires-Dist: Pillow (>=7.2.0)
Requires-Dist: pytesseract (>=0.3.4)
